youngersibling/__init__.py
youngersibling/data.json
youngersibling/display_table.py
youngersibling/email_lookup.py
youngersibling/exif_data_extraction.py
youngersibling/google_search.py
youngersibling/ip_lookup.py
youngersibling/main.py
youngersibling/phone_lookup.py
youngersibling/username_lookup.py
youngersibling/web_osint.py
youngersibling-1.2.dist-info/LICENSE
youngersibling-1.2.dist-info/METADATA
youngersibling-1.2.dist-info/WHEEL
youngersibling-1.2.dist-info/entry_points.txt
youngersibling-1.2.dist-info/top_level.txt
youngersibling-1.2.dist-info/RECORD
