Metadata-Version: 2.1
Name: youngersibling
Version: 1.2
Summary: An educational OSINT toolkit for research and analysis.
Home-page: https://github.com/Mostafizur-Rahman8391/YoungerSibling
Author: Mostafizur Rahman
Author-email: mostafizurrahman8391@gmail.com
License: MIT
Classifier: Programming Language :: Python :: 3
Classifier: License :: OSI Approved :: MIT License
Classifier: Operating System :: OS Independent
Requires-Python: >=3.7
License-File: LICENSE
Requires-Dist: requests
Requires-Dist: beautifulsoup4
Requires-Dist: colorama
Requires-Dist: terminaltables
Requires-Dist: dnspython
Requires-Dist: exifread
Requires-Dist: tqdm
Requires-Dist: python-whois
Requires-Dist: datetime
Requires-Dist: phonenumbers
